{
  "run_id": "run_20250803_225635",
  "start_time": "2025-08-03T22:56:35.749727",
  "workflow": "fetch_and_place",
  "steps": [
    {
      "timestamp": "2025-08-03T22:56:35.858611",
      "skill": "Sequence",
      "status": "RUNNING",
      "duration": 0.0
    },
    {
      "timestamp": "2025-08-03T22:56:35.941869",
      "skill": "Sequence",
      "status": "RUNNING",
      "duration": 0.0
    },
    {
      "timestamp": "2025-08-03T22:56:36.024589",
      "skill": "Sequence",
      "status": "RUNNING",
      "duration": 0.0
    },
    {
      "timestamp": "2025-08-03T22:56:36.104554",
      "skill": "Sequence",
      "status": "RUNNING",
      "duration": 0.0
    },
    {
      "timestamp": "2025-08-03T22:56:36.185859",
      "skill": "Sequence",
      "status": "RUNNING",
      "duration": 0.0
    },
    {
      "timestamp": "2025-08-03T22:56:36.266924",
      "skill": "Sequence",
      "status": "RUNNING",
      "duration": 0.0
    },
    {
      "timestamp": "2025-08-03T22:56:36.343569",
      "skill": "Sequence",
      "status": "RUNNING",
      "duration": 0.0
    },
    {
      "timestamp": "2025-08-03T22:56:36.422779",
      "skill": "Sequence",
      "status": "RUNNING",
      "duration": 0.0
    },
    {
      "timestamp": "2025-08-03T22:56:36.510252",
      "skill": "Sequence",
      "status": "RUNNING",
      "duration": 0.0
    },
    {
      "timestamp": "2025-08-03T22:56:36.590971",
      "skill": "Sequence",
      "status": "RUNNING",
      "duration": 0.0
    },
    {
      "timestamp": "2025-08-03T22:56:36.670547",
      "skill": "Sequence",
      "status": "RUNNING",
      "duration": 0.0
    },
    {
      "timestamp": "2025-08-03T22:56:36.751156",
      "skill": "Sequence",
      "status": "RUNNING",
      "duration": 0.0
    },
    {
      "timestamp": "2025-08-03T22:56:36.830026",
      "skill": "Sequence",
      "status": "RUNNING",
      "duration": 0.0
    },
    {
      "timestamp": "2025-08-03T22:56:38.344890",
      "skill": "Sequence",
      "status": "RUNNING",
      "duration": 0.0
    },
    {
      "timestamp": "2025-08-03T22:56:38.435514",
      "skill": "Sequence",
      "status": "RUNNING",
      "duration": 0.0
    },
    {
      "timestamp": "2025-08-03T22:56:38.529747",
      "skill": "Sequence",
      "status": "RUNNING",
      "duration": 0.0
    },
    {
      "timestamp": "2025-08-03T22:56:38.621429",
      "skill": "Sequence",
      "status": "RUNNING",
      "duration": 0.0
    },
    {
      "timestamp": "2025-08-03T22:56:38.707479",
      "skill": "Sequence",
      "status": "RUNNING",
      "duration": 0.0
    },
    {
      "timestamp": "2025-08-03T22:56:38.795505",
      "skill": "Sequence",
      "status": "RUNNING",
      "duration": 0.0
    },
    {
      "timestamp": "2025-08-03T22:56:38.884148",
      "skill": "Sequence",
      "status": "RUNNING",
      "duration": 0.0
    },
    {
      "timestamp": "2025-08-03T22:56:38.973767",
      "skill": "Sequence",
      "status": "RUNNING",
      "duration": 0.0
    },
    {
      "timestamp": "2025-08-03T22:56:39.060440",
      "skill": "Sequence",
      "status": "RUNNING",
      "duration": 0.0
    },
    {
      "timestamp": "2025-08-03T22:56:39.155143",
      "skill": "Sequence",
      "status": "RUNNING",
      "duration": 0.0
    },
    {
      "timestamp": "2025-08-03T22:56:39.248898",
      "skill": "Sequence",
      "status": "RUNNING",
      "duration": 0.0
    },
    {
      "timestamp": "2025-08-03T22:56:39.340239",
      "skill": "Sequence",
      "status": "RUNNING",
      "duration": 0.0
    },
    {
      "timestamp": "2025-08-03T22:56:39.431966",
      "skill": "Sequence",
      "status": "RUNNING",
      "duration": 0.0
    },
    {
      "timestamp": "2025-08-03T22:56:39.518045",
      "skill": "Sequence",
      "status": "RUNNING",
      "duration": 0.0
    },
    {
      "timestamp": "2025-08-03T22:56:39.606501",
      "skill": "Sequence",
      "status": "RUNNING",
      "duration": 0.0
    },
    {
      "timestamp": "2025-08-03T22:56:39.695561",
      "skill": "Sequence",
      "status": "RUNNING",
      "duration": 0.0
    },
    {
      "timestamp": "2025-08-03T22:56:39.787069",
      "skill": "Sequence",
      "status": "RUNNING",
      "duration": 0.0
    },
    {
      "timestamp": "2025-08-03T22:56:39.874727",
      "skill": "Sequence",
      "status": "RUNNING",
      "duration": 0.0
    },
    {
      "timestamp": "2025-08-03T22:56:39.961761",
      "skill": "Sequence",
      "status": "RUNNING",
      "duration": 0.0
    },
    {
      "timestamp": "2025-08-03T22:56:40.050130",
      "skill": "Sequence",
      "status": "RUNNING",
      "duration": 0.0
    },
    {
      "timestamp": "2025-08-03T22:56:40.138193",
      "skill": "Sequence",
      "status": "RUNNING",
      "duration": 0.0
    },
    {
      "timestamp": "2025-08-03T22:56:40.223152",
      "skill": "Sequence",
      "status": "RUNNING",
      "duration": 0.0
    },
    {
      "timestamp": "2025-08-03T22:56:40.309416",
      "skill": "Sequence",
      "status": "RUNNING",
      "duration": 0.0
    },
    {
      "timestamp": "2025-08-03T22:56:44.573004",
      "skill": "Sequence",
      "status": "SUCCESS",
      "duration": 0.0
    }
  ],
  "total_duration": 8.82334017753601,
  "failures": 0,
  "recovery_steps": 0,
  "teleop_interventions": 0,
  "final_status": "SUCCESS",
  "end_time": "2025-08-03T22:56:44.573122"
}